.hgignore
README.rst
setup.py
django_postfix/__init__.py
django_postfix/admin.py
django_postfix/models.py
django_postfix/tests.py
django_postfix/views.py
django_postfix.egg-info/PKG-INFO
django_postfix.egg-info/SOURCES.txt
django_postfix.egg-info/dependency_links.txt
django_postfix.egg-info/requires.txt
django_postfix.egg-info/top_level.txt
django_postfix.egg-info/zip-safe
django_postfix/migrations/0001_initial.py
django_postfix/migrations/__init__.py