Metadata-Version: 1.0
Name: django-postfix
Version: 0.0.1dev
Summary: A django app to manage postfix mailboxes
Home-page: http://bitbucket.org/creat1va/django-postfix
Author: Mario César Señoranis Ayala
Author-email: mariocesar.c50@gmail.com
License: MIT License
Keywords: postfix mail django
Platform: UNKNOWN
Classifier: Development Status :: 1 - Planning
Classifier: Environment :: Web Environment
Classifier: Framework :: Django
Classifier: Intended Audience :: Developers
Classifier: License :: OSI Approved :: MIT License
Classifier: Operating System :: OS Independent
Classifier: Programming Language :: Python
Classifier: Topic :: Software Development :: Libraries :: Python Modules
